source_apple_search_ads/__init__.py
source_apple_search_ads/manifest.yaml
source_apple_search_ads/run.py
source_apple_search_ads/schemas/adgroups.json
source_apple_search_ads/schemas/adgroups_report_daily.json
source_apple_search_ads/schemas/campaigns.json
source_apple_search_ads/schemas/campaigns_report_daily.json
source_apple_search_ads/schemas/keywords.json
source_apple_search_ads/schemas/keywords_report_daily.json
source_apple_search_ads/source.py
source_apple_search_ads/spec.yaml
airbyte_source_apple_search_ads-0.1.20.dist-info/METADATA
airbyte_source_apple_search_ads-0.1.20.dist-info/WHEEL
airbyte_source_apple_search_ads-0.1.20.dist-info/entry_points.txt
airbyte_source_apple_search_ads-0.1.20.dist-info/RECORD
